atomistica-1.2.7.dist-info/WHEEL
atomistica-1.2.7.dist-info/METADATA
atomistica-1.2.7.dist-info/RECORD
atomistica/logger.py
atomistica/hardware.py
atomistica/native.py
atomistica/_atomistica.cpython-312-x86_64-linux-gnu.so
atomistica/analysis.py
atomistica/snippets.py
atomistica/join_calculators.py
atomistica/atomic_strain.py
atomistica/deformation.py
atomistica/parameters.py
atomistica/__init__.py
atomistica/tests.py
atomistica/aseinterface.py
atomistica/mdcore_io.py
atomistica/io.py
atomistica/tools/a_convert.py
atomistica/tools/a_angle_distribution.py
atomistica/tools/a_run.py
atomistica/tools/a_fire.py
atomistica/tools/a_voro.py
atomistica/tools/a_g2.py
atomistica.libs/libblas-357956a1.so.3.4.2
atomistica.libs/libquadmath-96973f99.so.0.0.0
atomistica.libs/libgfortran-91cc3cb1.so.3.0.0
atomistica.libs/libgfortran-040039e1.so.5.0.0
atomistica.libs/liblapack-1ad85175.so.3.4.2
