Metadata-Version: 2.1
Name: atomistica
Version: 1.2.7
Summary: Atomistica is a library of interatomic potentials that is compatible with ASE and LAMMPS
Maintainer-Email: Lars Pastewka <lars.pastewka@imtek.uni-freiburg.de>
License: GPL-2.0-or-later
Project-URL: homepage, https://github.com/Atomistica/atomistica
Requires-Python: >=3.9
Requires-Dist: numpy>=1.21.0
Requires-Dist: ase>=3.15.0
Requires-Dist: pip>=25.2
